top/__init__.py
top/api/__init__.py
top/api/base.py
top/api/rest/AlipayXiaodaiUserPermitRequest.py
top/api/rest/AppipGetRequest.py
top/api/rest/FilesGetRequest.py
top/api/rest/HttpdnsGetRequest.py
top/api/rest/KfcKeywordSearchRequest.py
top/api/rest/OpenuidChangeRequest.py
top/api/rest/OpenuidGetBymixnickRequest.py
top/api/rest/OpenuidGetBytradeRequest.py
top/api/rest/OpenuidGetRequest.py
top/api/rest/TimeGetRequest.py
top/api/rest/TmallCrmMemberFrontUnbindRequest.py
top/api/rest/TmallCrmMemberPointChangeRequest.py
top/api/rest/TmallMeiCrmCallbackPointChangeRequest.py
top/api/rest/TmallMeiCrmMemberSyncRequest.py
top/api/rest/TmcAuthGetRequest.py
top/api/rest/TmcGroupAddRequest.py
top/api/rest/TmcGroupDeleteRequest.py
top/api/rest/TmcGroupsGetRequest.py
top/api/rest/TmcMessageProduceRequest.py
top/api/rest/TmcMessagesConfirmRequest.py
top/api/rest/TmcMessagesConsumeRequest.py
top/api/rest/TmcMessagesProduceRequest.py
top/api/rest/TmcMsgSendrecordRequest.py
top/api/rest/TmcQueueGetRequest.py
top/api/rest/TmcTopicGroupAddRequest.py
top/api/rest/TmcTopicGroupDeleteRequest.py
top/api/rest/TmcUserCancelRequest.py
top/api/rest/TmcUserGetRequest.py
top/api/rest/TmcUserPermitRequest.py
top/api/rest/TmcUserTopicsGetRequest.py
top/api/rest/TopAuthTokenCreateRequest.py
top/api/rest/TopAuthTokenRefreshRequest.py
top/api/rest/TopIpoutGetRequest.py
top/api/rest/TopSdkFeedbackUploadRequest.py
top/api/rest/TopSecretGetRequest.py
top/api/rest/TopSecretRegisterRequest.py
top/api/rest/WangwangClientidBindRequest.py
top/api/rest/WangwangClientidUnbindRequest.py
top/api/rest/__init__.py
taobao_sdk_top-0.0.1.dist-info/METADATA
taobao_sdk_top-0.0.1.dist-info/WHEEL
taobao_sdk_top-0.0.1.dist-info/top_level.txt
taobao_sdk_top-0.0.1.dist-info/RECORD
