Metadata-Version: 2.1
Name: taobao-sdk-top
Version: 0.0.1
Summary: taobao sdk for python 3
Home-page: https://github.com/sl40/taobao-sdk
Author: silin
Author-email: silinwork@gmail.com
License: UNKNOWN
Platform: UNKNOWN
Classifier: Programming Language :: Python :: 3
Classifier: License :: OSI Approved :: MIT License
Classifier: Operating System :: OS Independent
